odoo8_addon_product_margin_classification-8.0.2.1.0-py2.7-nspkg.pth
odoo8_addon_product_margin_classification-8.0.2.1.0.dist-info/METADATA
odoo8_addon_product_margin_classification-8.0.2.1.0.dist-info/RECORD
odoo8_addon_product_margin_classification-8.0.2.1.0.dist-info/WHEEL
odoo8_addon_product_margin_classification-8.0.2.1.0.dist-info/namespace_packages.txt
odoo8_addon_product_margin_classification-8.0.2.1.0.dist-info/top_level.txt
odoo_addons/product_margin_classification/README.rst
odoo_addons/product_margin_classification/__init__.py
odoo_addons/product_margin_classification/__openerp__.py
odoo_addons/product_margin_classification/data/decimal_precision.xml
odoo_addons/product_margin_classification/demo/product_margin_classification.xml
odoo_addons/product_margin_classification/demo/product_template.xml
odoo_addons/product_margin_classification/demo/res_groups.yml
odoo_addons/product_margin_classification/i18n/am.po
odoo_addons/product_margin_classification/i18n/ar.po
odoo_addons/product_margin_classification/i18n/bg.po
odoo_addons/product_margin_classification/i18n/bs.po
odoo_addons/product_margin_classification/i18n/ca.po
odoo_addons/product_margin_classification/i18n/ca_ES.po
odoo_addons/product_margin_classification/i18n/cs.po
odoo_addons/product_margin_classification/i18n/da.po
odoo_addons/product_margin_classification/i18n/de.po
odoo_addons/product_margin_classification/i18n/el_GR.po
odoo_addons/product_margin_classification/i18n/en_GB.po
odoo_addons/product_margin_classification/i18n/es.po
odoo_addons/product_margin_classification/i18n/es_AR.po
odoo_addons/product_margin_classification/i18n/es_CL.po
odoo_addons/product_margin_classification/i18n/es_CO.po
odoo_addons/product_margin_classification/i18n/es_CR.po
odoo_addons/product_margin_classification/i18n/es_DO.po
odoo_addons/product_margin_classification/i18n/es_EC.po
odoo_addons/product_margin_classification/i18n/es_ES.po
odoo_addons/product_margin_classification/i18n/es_MX.po
odoo_addons/product_margin_classification/i18n/es_PE.po
odoo_addons/product_margin_classification/i18n/es_PY.po
odoo_addons/product_margin_classification/i18n/es_VE.po
odoo_addons/product_margin_classification/i18n/et.po
odoo_addons/product_margin_classification/i18n/fa.po
odoo_addons/product_margin_classification/i18n/fi.po
